pvduck/__init__.py
pvduck/cli.py
pvduck/config.py
pvduck/db.py
pvduck/project.py
pvduck/stream.py
pvduck/timeseries.py
pvduck/validators.py
pvduck/wikimedia.py
pvduck-0.1.0.dist-info/licenses/LICENSE.md
pvduck-0.1.0.dist-info/WHEEL
pvduck-0.1.0.dist-info/entry_points.txt
pvduck-0.1.0.dist-info/METADATA
pvduck-0.1.0.dist-info/RECORD
