Metadata-Version: 2.4
Name: pvduck
Version: 0.1.0
Summary: Load Wikimedia pageview data to a duckdb
Keywords: wikimedia,pageviews,wikipedia,duckdb,analytics,data-pipeline
Author: Vegard Egeland
Author-email: Vegard Egeland <vegardegeland@gmail.com>
License-Expression: MIT
License-File: LICENSE.md
Classifier: Development Status :: 4 - Beta
Classifier: Environment :: Console
Classifier: Intended Audience :: Developers
Classifier: Intended Audience :: Science/Research
Classifier: License :: OSI Approved :: MIT License
Classifier: Operating System :: OS Independent
Classifier: Topic :: Database
Classifier: Topic :: Internet :: Log Analysis
Classifier: Topic :: Scientific/Engineering :: Information Analysis
Classifier: Typing :: Typed
Requires-Dist: duckdb>=1.4.1,<2.0.0
Requires-Dist: pvstream==0.1.0
Requires-Dist: pydantic>=2.12.2,<3.0.0
Requires-Dist: pyyaml>=6.0.3,<7.0.0
Requires-Dist: typer>=0.19.2,<1.0.0
Requires-Python: >=3.10
Project-URL: Bug, https://github.com/vegardege/pvduck/issues
Project-URL: Changelog, https://github.com/vegardege/pvduck/blob/master/CHANGELOG.md
Project-URL: Documentation, https://github.com/vegardege/pvduck
Project-URL: Repository, https://github.com/vegardege/pvduck
